open_octopus/__init__.py
open_octopus/agent.py
open_octopus/cli.py
open_octopus/client.py
open_octopus/menubar.py
open_octopus/models.py
open_octopus-0.3.0.dist-info/METADATA
open_octopus-0.3.0.dist-info/WHEEL
open_octopus-0.3.0.dist-info/entry_points.txt
open_octopus-0.3.0.dist-info/licenses/LICENSE
open_octopus-0.3.0.dist-info/RECORD
