Metadata-Version: 2.4
Name: open-octopus
Version: 0.3.0
Summary: Modern async Python client for the Octopus Energy GraphQL API
Project-URL: Homepage, https://github.com/abracadabra50/open-octopus
Project-URL: Documentation, https://github.com/abracadabra50/open-octopus#readme
Project-URL: Repository, https://github.com/abracadabra50/open-octopus
Project-URL: Issues, https://github.com/abracadabra50/open-octopus/issues
Author-email: Zishan <zishan@example.com>
License-Expression: MIT
License-File: LICENSE
Keywords: api-client,async,electricity,energy,graphql,home-mini,intelligent-octopus,octopus-energy,smart-meter
Classifier: Development Status :: 4 - Beta
Classifier: Environment :: Console
Classifier: Framework :: AsyncIO
Classifier: Intended Audience :: Developers
Classifier: License :: OSI Approved :: MIT License
Classifier: Operating System :: OS Independent
Classifier: Programming Language :: Python :: 3
Classifier: Programming Language :: Python :: 3.10
Classifier: Programming Language :: Python :: 3.11
Classifier: Programming Language :: Python :: 3.12
Classifier: Topic :: Home Automation
Classifier: Topic :: Software Development :: Libraries :: Python Modules
Classifier: Typing :: Typed
Requires-Python: >=3.10
Requires-Dist: httpx>=0.25.0
Requires-Dist: rich>=13.0.0
Requires-Dist: typer>=0.9.0
Provides-Extra: agent
Requires-Dist: anthropic>=0.30.0; extra == 'agent'
Provides-Extra: all
Requires-Dist: anthropic>=0.30.0; extra == 'all'
Requires-Dist: rumps>=0.4.0; extra == 'all'
Provides-Extra: dev
Requires-Dist: mypy>=1.5.0; extra == 'dev'
Requires-Dist: pytest-asyncio>=0.21.0; extra == 'dev'
Requires-Dist: pytest-cov>=4.0.0; extra == 'dev'
Requires-Dist: pytest>=7.0.0; extra == 'dev'
Requires-Dist: ruff>=0.1.0; extra == 'dev'
Provides-Extra: menubar
Requires-Dist: rumps>=0.4.0; extra == 'menubar'
